pyabi_smf/__init__.py
tests/__init__.py
tests/test_pyabi_smf.py
PyABI_SMF-5.42.10.dist-info/METADATA
PyABI_SMF-5.42.10.dist-info/WHEEL
PyABI_SMF-5.42.10.dist-info/top_level.txt
PyABI_SMF-5.42.10.dist-info/RECORD
