Metadata-Version: 2.1
Name: PyABI-SMF
Version: 5.42.10
Summary: The PyABI bindings for the 'Self Maintaining Format' used by FileCensus.
Home-page: https://intermine.com
Author: Scott McCallum (https intermine.com)
Author-email: sales@intermine.com
License: UNKNOWN
Platform: UNKNOWN
Classifier: Programming Language :: Python :: 3
Classifier: Operating System :: OS Independent
Requires-Python: >=3.6
